{
  "/404": "pages/404.html",
  "/_app": "pages/_app.js",
  "/api/account/[id]": "pages/api/account/[id].js",
  "/api/account": "pages/api/account.js",
  "/api/account/password": "pages/api/account/password.js",
  "/api/accounts": "pages/api/accounts.js",
  "/api/auth/login": "pages/api/auth/login.js",
  "/api/auth/logout": "pages/api/auth/logout.js",
  "/api/auth/verify": "pages/api/auth/verify.js",
  "/api/collect": "pages/api/collect.js",
  "/api/realtime/init": "pages/api/realtime/init.js",
  "/api/realtime/update": "pages/api/realtime/update.js",
  "/api/share/[id]": "pages/api/share/[id].js",
  "/api/website/[id]/active": "pages/api/website/[id]/active.js",
  "/api/website/[id]/events": "pages/api/website/[id]/events.js",
  "/api/website/[id]": "pages/api/website/[id].js",
  "/api/website/[id]/metrics": "pages/api/website/[id]/metrics.js",
  "/api/website/[id]/pageviews": "pages/api/website/[id]/pageviews.js",
  "/api/website/[id]/stats": "pages/api/website/[id]/stats.js",
  "/api/website": "pages/api/website.js",
  "/api/websites": "pages/api/websites.js",
  "/dashboard/[[...id]]": "pages/dashboard/[[...id]].html",
  "/": "pages/index.html",
  "/login": "pages/login.html",
  "/logout": "pages/logout.html",
  "/realtime": "pages/realtime.html",
  "/settings/accounts": "pages/settings/accounts.html",
  "/settings": "pages/settings.html",
  "/settings/profile": "pages/settings/profile.html",
  "/share/[...id]": "pages/share/[...id].html",
  "/test": "pages/test.html",
  "/website/[...id]": "pages/website/[...id].html",
  "/_error": "pages/_error.js",
  "/_document": "pages/_document.js"
}